btutils/__init__.py
btutils/btutils.py
btutils-0.1.2.dist-info/METADATA
btutils-0.1.2.dist-info/WHEEL
btutils-0.1.2.dist-info/top_level.txt
btutils-0.1.2.dist-info/RECORD
