Metadata-Version: 2.4
Name: btutils
Version: 0.1.2
Summary: A lightweight Python library for backtesting analysis and visualization of trading strategies
Requires-Python: >=3.7
Requires-Dist: matplotlib>=3.3.0
Requires-Dist: pandas>=1.0.0
Requires-Dist: scipy>=1.5.0
Requires-Dist: seaborn>=0.11.0
Requires-Dist: tabulate>=0.8.0
Provides-Extra: dev
Requires-Dist: twine; extra == "dev"
Requires-Dist: build; extra == "dev"
